pacfish/__init__.py
pacfish/visualize_device.py
pacfish/api/BaseAdapter.py
pacfish/api/__init__.py
pacfish/api/adapters/Cyberdyne_Converter.py
pacfish/api/adapters/Nrrd_File_Converter.py
pacfish/api/adapters/__init__.py
pacfish/core/DeviceMetaDataCreator.py
pacfish/core/Metadata.py
pacfish/core/PAData.py
pacfish/core/__init__.py
pacfish/iohandler/__init__.py
pacfish/iohandler/file_reader.py
pacfish/iohandler/file_writer.py
pacfish/qualitycontrol/CompletenessChecker.py
pacfish/qualitycontrol/ConsistencyChecker.py
pacfish/qualitycontrol/PADataIntegrityCheck.py
pacfish/qualitycontrol/PrintAllMetadataContainedInIPASCFile.py
pacfish/qualitycontrol/__init__.py
pacfish-0.4.4.dist-info/METADATA
pacfish-0.4.4.dist-info/WHEEL
pacfish-0.4.4.dist-info/top_level.txt
pacfish-0.4.4.dist-info/RECORD
