Metadata-Version: 2.1
Name: pacfish
Version: 0.4.4
Summary: Photoacoustic Converter for Information Sharing (PACFISH)
Home-page: https://github.com/IPASC/PACFISH/
Author: International Photoacoustic Standardisation Consortium (IPASC)
Author-email: janek.grohl@cruk.cam.ac.uk
License: BSD-3-Clause
Project-URL: Bug Tracker, https://github.com/IPASC/PACFISH/issues
Classifier: Programming Language :: Python :: 3
Classifier: License :: OSI Approved :: BSD License
Classifier: Operating System :: OS Independent
Requires-Python: >=3.7
Requires-Dist: numpy
Requires-Dist: matplotlib
Requires-Dist: h5py
Requires-Dist: pynrrd
Requires-Dist: myst-parser
Requires-Dist: coverage
Requires-Dist: pytest-cov
Requires-Dist: imageio
Requires-Dist: scipy
